LICENSE
MANIFEST.in
README.rst
setup.py
demo/__init__.py
demo/__main__.py
demo/bootstrap.py
demo/stuff.py
sectemp_bootstrap.egg-info/PKG-INFO
sectemp_bootstrap.egg-info/SOURCES.txt
sectemp_bootstrap.egg-info/dependency_links.txt
sectemp_bootstrap.egg-info/entry_points.txt
sectemp_bootstrap.egg-info/top_level.txt