Metadata-Version: 1.0
Name: sectemp-bootstrap
Version: 0.2.1
Summary: Python command line application bare bones template.
Home-page: something
Author: SP
Author-email: sp@wacko.com
License: UNKNOWN
Platform: UNKNOWN
